Metadata-Version: 2.1
Name: odoo12-addon-web-company-color
Version: 12.0.1.2.0
Summary: Web Company Color
Home-page: https://github.com/OCA/web
Author: Alexandre Díaz, Odoo Community Association (OCA)
Author-email: support@odoo-community.org
License: AGPL-3
Platform: UNKNOWN
Classifier: Programming Language :: Python
Classifier: Framework :: Odoo
Classifier: License :: OSI Approved :: GNU Affero General Public License v3
Requires-Python: >=3.5
Requires-Dist: odoo12-addon-web-widget-color
Requires-Dist: odoo (<12.1dev,>=12.0a)
